main.py
crypto_sentiment_mcp-0.1.0.dist-info/licenses/LICENSE
crypto_sentiment_mcp-0.1.0.dist-info/METADATA
crypto_sentiment_mcp-0.1.0.dist-info/WHEEL
crypto_sentiment_mcp-0.1.0.dist-info/top_level.txt
crypto_sentiment_mcp-0.1.0.dist-info/RECORD
